ecsmanage/__init__.py
ecsmanage/apps.py
ecsmanage/management/__init__.py
ecsmanage/management/commands/__init__.py
ecsmanage/management/commands/ecsmanage.py
tests/__init__.py
tests/settings_test.py
tests/test_configuration.py
django_ecsmanage-4.0.1.dist-info/LICENSE
django_ecsmanage-4.0.1.dist-info/METADATA
django_ecsmanage-4.0.1.dist-info/WHEEL
django_ecsmanage-4.0.1.dist-info/top_level.txt
django_ecsmanage-4.0.1.dist-info/RECORD
