Metadata-Version: 2.1
Name: django-ecsmanage
Version: 4.0.1
Summary: Run any Django management command on an AWS Elastic Container Service (ECS) cluster.
Home-page: https://github.com/azavea/django-ecsmanage/
Author: Azavea, Inc.
Author-email: systems@azavea.com
License: Apache License 2.0
Classifier: Environment :: Web Environment
Classifier: Framework :: Django
Classifier: Framework :: Django :: 3.2
Classifier: Framework :: Django :: 4.2
Classifier: Framework :: Django :: 5.0
Classifier: Intended Audience :: Developers
Classifier: License :: OSI Approved :: Apache Software License
Classifier: Programming Language :: Python
Classifier: Programming Language :: Python :: 3
Classifier: Programming Language :: Python :: 3 :: Only
Classifier: Programming Language :: Python :: 3.8
Classifier: Programming Language :: Python :: 3.10
Classifier: Programming Language :: Python :: 3.12
Requires-Python: >=3.8
License-File: LICENSE
Requires-Dist: Django >=2.2
Requires-Dist: boto3 >=1.9.0
Provides-Extra: tests
Requires-Dist: flake8 >=3.7.7 ; extra == 'tests'
Requires-Dist: black ; (python_version > "3.8") and extra == 'tests'
